bankroll/model/__init__.py
bankroll/model/activity.py
bankroll/model/balance.py
bankroll/model/cash.py
bankroll/model/converter.py
bankroll/model/instrument.py
bankroll/model/position.py
bankroll/model/py.typed
bankroll/model/quote.py
bankroll_model-0.4.1.dist-info/LICENSE
bankroll_model-0.4.1.dist-info/METADATA
bankroll_model-0.4.1.dist-info/WHEEL
bankroll_model-0.4.1.dist-info/top_level.txt
bankroll_model-0.4.1.dist-info/RECORD
